pycmc/__init__.py
pycmc/album.py
pycmc/artist.py
pycmc/background.py
pycmc/chart_cleaners.py
pycmc/credentials.py
pycmc/credentials_manager.py
pycmc/curator.py
pycmc/playlist.py
pycmc/recommendation.py
pycmc/search_engine.py
pycmc/track.py
pycmc/utilities.py
pycmc/charts/__init__.py
pycmc/charts/amazon.py
pycmc/charts/applemusic.py
pycmc/charts/beatport.py
pycmc/charts/cm_score.py
pycmc/charts/deezer.py
pycmc/charts/itunes.py
pycmc/charts/qq.py
pycmc/charts/shazam.py
pycmc/charts/soundcloud.py
pycmc/charts/spotify.py
pycmc/charts/youtube.py
pycmc-0.0.11.dist-info/LICENSE
pycmc-0.0.11.dist-info/METADATA
pycmc-0.0.11.dist-info/WHEEL
pycmc-0.0.11.dist-info/top_level.txt
pycmc-0.0.11.dist-info/RECORD
