Metadata-Version: 2.1
Name: pycmc
Version: 0.0.11
Summary: A Python client for the chartmetric.com API, by Musicfox.
Home-page: https://github.com/musicfox/pycmc
Author: Jason R. Stevens, CFA | Musicfox, Inc. | musicfox.io
Author-email: dev@musicfox.io
License: MIT
Project-URL: Documentation, https://pycmc.docs.musicfox.io
Project-URL: Bug Reports, https://github.com/musicfox/pycmc/issues
Project-URL: Source Code, https://github.com/musicfox/pycmc
Project-URL: Musicfox, https://musicfox.io
Project-URL: Musicfox Fan.Booster, https://fan.booster.musicfox.io
Project-URL: Musicfox Dev, https://twitter.com/MusicfoxDev
Platform: UNKNOWN
Classifier: License :: OSI Approved :: MIT License
Classifier: Programming Language :: Python
Classifier: Programming Language :: Python :: 3
Classifier: Programming Language :: Python :: 3.8
Classifier: Programming Language :: Python :: 3.9
Classifier: Development Status :: 3 - Alpha
Classifier: Topic :: Scientific/Engineering :: Information Analysis
Classifier: Intended Audience :: Developers
Classifier: Intended Audience :: Education
Classifier: Intended Audience :: Financial and Insurance Industry
Classifier: Intended Audience :: Information Technology
Classifier: Intended Audience :: Other Audience
Classifier: Intended Audience :: Science/Research
Classifier: Intended Audience :: Telecommunications Industry
Requires-Python: >=3.8.0
Requires-Dist: numpy (>=1.0.0)
Requires-Dist: pandas (>=1.0.0)
Requires-Dist: requests (>=2.0.0)
